topsis_siddharth/__init__.py
topsis_siddharth/cli.py
topsis_siddharth/core.py
topsis_siddharth/validation.py
topsis_siddharth_102303592-1.0.1.dist-info/licenses/LICENSE
topsis_siddharth_102303592-1.0.1.dist-info/METADATA
topsis_siddharth_102303592-1.0.1.dist-info/WHEEL
topsis_siddharth_102303592-1.0.1.dist-info/entry_points.txt
topsis_siddharth_102303592-1.0.1.dist-info/top_level.txt
topsis_siddharth_102303592-1.0.1.dist-info/RECORD
