Metadata-Version: 2.4
Name: Topsis-Siddharth-102303592
Version: 1.0.1
Summary: A command-line implementation of TOPSIS (MCDM) in Python
Author-email: Siddharth Jaswal <siddy32jaswal@gmail.com>
License: MIT
Requires-Python: >=3.8
License-File: LICENSE
Requires-Dist: numpy
Requires-Dist: pandas
Dynamic: license-file
